[{"customerDetails":{"name":"RAJESH","address":"CHARKOP TIRUPATI BALAJI,C","mob":"9004659569","gstNO":"646463346436","pan":""},"productDetails":{"sn0":1,"productName0":"Gold ornament","gw0":"1.0","nw0":"1.0","rpu0":"5000","amount0":5000,"sn1":"","productName1":"","gw1":"","nw1":"","rpu1":"","amount1":"","sn2":2,"oldProductName":"old silver chain","oldGW":"1.0","oldNW":"1.0","oldRPU":"600","oldAmount":600},"other":{"discount":"0","mode":"cash","total":"4400.00","cgst":"66.00","sgst":"66.00","netAm":"4532.00","inWords":"Rupees Four Thousand Five Hundred And Thirty Two  Only."},"invoiceNo":"1500","date":"Feb 28 2022","pType":"gold"},{"customerDetails":{"name":"RAJESH","address":"CHARKOP TIRUPATI BALAJI,C","mob":"9004659569","gstNO":"646463346436","pan":""},"productDetails":{"sn0":1,"productName0":"Gold ornament","gw0":"1.0","nw0":"1.0","rpu0":"5000","amount0":5000,"sn1":"","productName1":"","gw1":"","nw1":"","rpu1":"","amount1":"","sn2":2,"oldProductName":"old silver chain","oldGW":"1.0","oldNW":"1.0","oldRPU":"600","oldAmount":600},"other":{"discount":"0","mode":"cash","total":"4400.00","cgst":"66.00","sgst":"66.00","netAm":"4532.00","inWords":"Rupees Four Thousand Five Hundred And Thirty Two  Only."},"invoiceNo":"1400","date":"Feb 28 2022","pType":"silver"},{"customerDetails":{"name":"Amit Vishwakarma","address":"INQALAB CHAWL AKURLI ROAD","mob":"9004659569","gstNO":"646463346436","pan":"AUUH#3353"},"productDetails":{"sn0":1,"productName0":"Gold ornament","gw0":"1.0","nw0":"1.0","rpu0":"03000","amount0":3000,"sn1":"","productName1":"","gw1":"","nw1":"","rpu1":"","amount1":"","sn2":2,"oldProductName":"old silver chain","oldGW":"1.0","oldNW":"1.0","oldRPU":"600","oldAmount":600},"other":{"discount":"0","mode":"Cash","total":"2400.00","cgst":"36.00","sgst":"36.00","netAm":"2472.00","inWords":"Rupees Two Thousand Four Hundred And Seventy Two  Only."},"invoiceNo":1501,"date":"Feb 28 2022","pType":"gold"},{"customerDetails":{"name":"MAHENDRA","address":"shop no.1,ARIHANT BUILDIN","mob":"9930151917","gstNO":"2AJDUFKK3u4944","pan":""},"productDetails":{"sn0":1,"productName0":"Gold ornament","gw0":"1.0","nw0":"1.0","rpu0":"4000","amount0":4000,"sn1":"","productName1":"","gw1":"","nw1":"","rpu1":"","amount1":"","sn2":"","oldProductName":"","oldGW":"","oldNW":"","oldRPU":"","oldAmount":""},"other":{"discount":"","mode":"","total":"4000.00","cgst":"60.00","sgst":"60.00","netAm":"4120.00","inWords":"Rupees Four Thousand One Hundred And Twenty  Only."},"invoiceNo":1502,"date":"","pType":"gold"},{"customerDetails":{"name":"MAHESH","address":"INQALAB CHAWL AKURLI ROAD","mob":"9004659569","gstNO":"","pan":""},"productDetails":{"sn0":1,"productName0":"Gold ornament","gw0":"1.0","nw0":"1.0","rpu0":"3000","amount0":3000,"sn1":"","productName1":"","gw1":"","nw1":"","rpu1":"","amount1":"","sn2":"","oldProductName":"","oldGW":"","oldNW":"","oldRPU":"","oldAmount":""},"other":{"discount":"","mode":"","total":"3000.00","cgst":"45.00","sgst":"45.00","netAm":"3090.00","inWords":"Rupees Three Thousand And Ninety  Only."},"invoiceNo":1503,"date":"","pType":"gold"},{"customerDetails":{"name":"MAHESH","address":"INQALAB CHAWL AKURLI ROAD","mob":"9004659569","gstNO":"","pan":""},"productDetails":{"sn0":1,"productName0":"Gold ornament","gw0":"1.0","nw0":"1.0","rpu0":"3000","amount0":3000,"sn1":"","productName1":"","gw1":"","nw1":"","rpu1":"","amount1":"","sn2":"","oldProductName":"","oldGW":"","oldNW":"","oldRPU":"","oldAmount":""},"other":{"discount":"","mode":"","total":"3000.00","cgst":"45.00","sgst":"45.00","netAm":"3090.00","inWords":"Rupees Three Thousand And Ninety  Only."},"invoiceNo":1504,"date":"","pType":"gold"},{"customerDetails":{"name":"MAHESH","address":"INQALAB CHAWL AKURLI ROAD","mob":"9004659569","gstNO":"","pan":""},"productDetails":{"sn0":1,"productName0":"Gold ornament","gw0":"1.0","nw0":"1.0","rpu0":"3000","amount0":3000,"sn1":"","productName1":"","gw1":"","nw1":"","rpu1":"","amount1":"","sn2":"","oldProductName":"","oldGW":"","oldNW":"","oldRPU":"","oldAmount":""},"other":{"discount":"","mode":"","total":"3000.00","cgst":"45.00","sgst":"45.00","netAm":"3090.00","inWords":"Rupees Three Thousand And Ninety  Only."},"invoiceNo":1505,"date":"","pType":"gold"},{"customerDetails":{"name":"MAHESH","address":"INQALAB CHAWL AKURLI ROAD","mob":"9004659569","gstNO":"","pan":""},"productDetails":{"sn0":1,"productName0":"Gold ornament","gw0":"1.0","nw0":"1.0","rpu0":"3000","amount0":3000,"sn1":"","productName1":"","gw1":"","nw1":"","rpu1":"","amount1":"","sn2":"","oldProductName":"","oldGW":"","oldNW":"","oldRPU":"","oldAmount":""},"other":{"discount":"","mode":"","total":"3000.00","cgst":"45.00","sgst":"45.00","netAm":"3090.00","inWords":"Rupees Three Thousand And Ninety  Only."},"invoiceNo":1506,"date":"","pType":"gold"},{"customerDetails":{"name":"","address":"","mob":"","gstNO":"","pan":""},"productDetails":{"sn0":1,"productName0":"Gold ornament","gw0":"1.0","nw0":"1.0","rpu0":"4444","amount0":4444,"sn1":"","productName1":"","gw1":"","nw1":"","rpu1":"","amount1":"","sn2":"","oldProductName":"","oldGW":"","oldNW":"","oldRPU":"","oldAmount":""},"other":{"discount":"","mode":"","total":"4444.00","cgst":"66.66","sgst":"66.66","netAm":"4577.00","inWords":"Rupees Four Thousand Five Hundred And Seventy Seven  Only."},"invoiceNo":1507,"date":"","pType":"gold"},{"customerDetails":{"name":"","address":"","mob":"","gstNO":"","pan":""},"productDetails":{"sn0":1,"productName0":"Gold ornament","gw0":"1.0","nw0":"01.0","rpu0":"0646456","amount0":646456,"sn1":"","productName1":"","gw1":"","nw1":"","rpu1":"","amount1":"","sn2":"","oldProductName":"","oldGW":"","oldNW":"","oldRPU":"","oldAmount":""},"other":{"discount":"","mode":"","total":"646456.00","cgst":"9696.84","sgst":"9696.84","netAm":"665850.00","inWords":"Rupees Six Lakh Sixty Five Thousand Eight Hundred And Fifty  Only."},"invoiceNo":1508,"date":"","pType":"gold"},{"customerDetails":{"name":"","address":"","mob":"","gstNO":"","pan":""},"productDetails":{"sn0":1,"productName0":"Gold ornament","gw0":"1.0","nw0":"1.0","rpu0":"300","amount0":300,"sn1":"","productName1":"","gw1":"","nw1":"","rpu1":"","amount1":"","sn2":"","oldProductName":"","oldGW":"","oldNW":"","oldRPU":"","oldAmount":""},"other":{"discount":"","mode":"","total":"300.00","cgst":"4.50","sgst":"4.50","netAm":"309.00","inWords":"Rupees Three Hundred And Nine  Only."},"invoiceNo":1509,"date":"","pType":"gold"},{"customerDetails":{"name":"","address":"","mob":"","gstNO":"","pan":""},"productDetails":{"sn0":1,"productName0":"Gold ornament","gw0":"1.0","nw0":"0","rpu0":"0","amount0":0,"sn1":"","productName1":"","gw1":"","nw1":"","rpu1":"","amount1":"","sn2":"","oldProductName":"","oldGW":"","oldNW":"","oldRPU":"","oldAmount":""},"other":{"discount":"","mode":"","total":"0.00","cgst":"0.00","sgst":"0.00","netAm":"0.00","inWords":"Rupees  Only."},"invoiceNo":1510,"date":"","pType":"gold"}]